sonoma/__init__.py
sonoma-1.0.12.dist-info/LICENSE
sonoma-1.0.12.dist-info/METADATA
sonoma-1.0.12.dist-info/WHEEL
sonoma-1.0.12.dist-info/top_level.txt
sonoma-1.0.12.dist-info/RECORD
