Metadata-Version: 2.1
Name: sonoma
Version: 1.0.12
Summary: A tiny, programmable http-server crafting-framework that is built with security and simplicity in mind.
Home-page: https://github.com/hostinfodev/sonoma
Author: hostinfodev
Author-email: support@host-info.net
License: MIT
Platform: UNKNOWN
Classifier: Programming Language :: Python :: 3
Classifier: License :: OSI Approved :: MIT License
Classifier: Operating System :: OS Independent
Classifier: Intended Audience :: Developers
Requires-Python: >=3.6
